stacrs_cli-0.5.0.dist-info/METADATA
stacrs_cli-0.5.0.dist-info/WHEEL
stacrs_cli-0.5.0.dist-info/entry_points.txt
stacrs_cli.libs/libgcc_s-b5472b99.so.1
stacrs_cli/__init__.py
stacrs_cli/ffi.py
stacrs_cli/libstacrs_cli.so
stacrs_cli-0.5.0.dist-info/RECORD
