Metadata-Version: 2.4
Name: stacrs-cli
Version: 0.5.0
Classifier: Development Status :: 3 - Alpha
Classifier: Intended Audience :: Science/Research
Classifier: Natural Language :: English
Classifier: Programming Language :: Rust
Classifier: Programming Language :: Python :: Implementation :: CPython
Classifier: Programming Language :: Python :: Implementation :: PyPy
Classifier: License :: OSI Approved :: Apache Software License
Classifier: License :: OSI Approved :: MIT License
Summary: A STAC command-line interface written in Rust
Keywords: stac,geospatial
Home-Page: https://stac-utils.github.io/stac-rs
Author: Pete Gadomski <pete.gadomski@gmail.com>
Author-email: Pete Gadomski <pete.gadomski@gmail.com>
License: MIT OR Apache-2.0
Requires-Python: >=3.8
Project-URL: Repository, https://github.com/stac-utils/stac-rs
Project-URL: Issues, https://github.com/stac-utils/stac-rs/issues
